whats2df/README.MD
whats2df/__init__.py
whats2df/requirements.txt
whats2df/thirdparty.json
whats2df/whats2df.py
whats2df-0.11.dist-info/LICENSE.rst
whats2df-0.11.dist-info/METADATA
whats2df-0.11.dist-info/WHEEL
whats2df-0.11.dist-info/top_level.txt
whats2df-0.11.dist-info/RECORD
