Metadata-Version: 2.1
Name: whats2df
Version: 0.11
Summary: Whatsapp to Pandas DataFrame (csv/xlsx/pkl) Doesn't require root access!
Home-page: https://github.com/hansalemaos/whats2df
Author: Johannes Fischer
Author-email: aulasparticularesdealemaosp@gmail.com
License: MIT
Keywords: whatsapp,pandas,DataFrame,convert
Classifier: Development Status :: 4 - Beta
Classifier: Programming Language :: Python :: 3 :: Only
Classifier: Programming Language :: Python :: 3.10
Classifier: Topic :: Software Development :: Libraries :: Python Modules
Classifier: Topic :: Utilities
License-File: LICENSE.rst
Requires-Dist: a-pandas-ex-read-sql
Requires-Dist: downloadunzip
Requires-Dist: hackyargparser
Requires-Dist: pandas
Requires-Dist: search-in-syspath
Requires-Dist: touchtouch
Requires-Dist: wa-crypt-tools
